LICENSE
README.md
setup.py
tryexcept_decorator/__init__.py
tryexcept_decorator/decorator.py
tryexcept_decorator.egg-info/PKG-INFO
tryexcept_decorator.egg-info/SOURCES.txt
tryexcept_decorator.egg-info/dependency_links.txt
tryexcept_decorator.egg-info/top_level.txt