Metadata-Version: 2.1
Name: tryexcept-decorator
Version: 0.1.7
Summary: See README
Home-page: https://github.com/davidedigrande/exception_handler_decorator
Author: Davide Di Grande
Author-email: davidedigrande.dev@gmail.com
Classifier: Development Status :: 3 - Alpha
Classifier: Programming Language :: Python :: 3
Classifier: License :: OSI Approved :: MIT License
Classifier: Operating System :: OS Independent
License-File: LICENSE
